LICENSE
README.md
setup.py
peernet/__init__.py
peernet/base_node.py
peernet/crypt.py
peernet/node_types.py
peernet.egg-info/PKG-INFO
peernet.egg-info/SOURCES.txt
peernet.egg-info/dependency_links.txt
peernet.egg-info/requires.txt
peernet.egg-info/top_level.txt